<?xml version="1.0" encoding="utf-8"?>
<proposicao tipo="REQ       " numero="739" ano="2015">
  <nomeProposicao>REQ 739/2015 =&gt; PL 6361/2013</nomeProposicao>
  <idProposicao>955528</idProposicao>
  <idProposicaoPrincipal>592333</idProposicaoPrincipal>
  <nomeProposicaoOrigem>
  </nomeProposicaoOrigem>
  <tipoProposicao>Requerimento de Urgência (Art. 155 do RICD)</tipoProposicao>
  <tema>
  </tema>
  <Ementa>Requer regime de urgência na apreciação do Projeto de Lei 6361 de 2013 que "denomina Rodovia PRESIDENTE NEREU RAMOS a BR-282 no Estado de Santa Catarina".</Ementa>
  <ExplicacaoEmenta>
  </ExplicacaoEmenta>
  <Autor>Esperidião Amin</Autor>
  <ideCadastro>160649</ideCadastro>
  <ufAutor>SC</ufAutor>
  <partidoAutor>PP        </partidoAutor>
  <DataApresentacao>03/03/2015</DataApresentacao>
  <RegimeTramitacao>.</RegimeTramitacao>
  <UltimoDespacho Data="">
  </UltimoDespacho>
  <Apreciacao>.</Apreciacao>
  <Indexacao>
  </Indexacao>
  <Situacao>MESA - Tramitação do Requerimento Finalizada</Situacao>
  <LinkInteiroTeor>http://www.camara.gov.br/proposicoesWeb/prop_mostrarintegra?codteor=1305021</LinkInteiroTeor>
  <apensadas />
</proposicao>