<?xml version="1.0" encoding="utf-8"?>
<proposicao>
  <Sigla>PLP</Sigla>
  <Numero>184</Numero>
  <Ano>2004</Ano>
  <Votacoes>
    <Votacao Resumo="Aprovado o Substitutivo adotado pela Comissão Especial. Sim: 330; Não: 0; Abst.: 0; Total: 330." Data="29/11/2006" Hora="19:50" ObjVotacao="SUBSTITUTIVO" codSessao="3024">
      <orientacaoBancada>
        <bancada Sigla="PT" orientacao="Sim            " />
        <bancada Sigla="PMDB" orientacao="Sim            " />
        <bancada Sigla="PFL" orientacao="Sim            " />
        <bancada Sigla="PSDB" orientacao="Sim            " />
        <bancada Sigla="PP" orientacao="Sim            " />
        <bancada Sigla="PTB" orientacao="Sim            " />
        <bancada Sigla="PL" orientacao="Sim            " />
        <bancada Sigla="PSB" orientacao="Sim            " />
        <bancada Sigla="PDT" orientacao="Sim            " />
        <bancada Sigla="PPS" orientacao="Sim            " />
        <bancada Sigla="PCdoB" orientacao="Sim            " />
        <bancada Sigla="PV" orientacao="Sim            " />
        <bancada Sigla="PSOL" orientacao="Sim            " />
        <bancada Sigla="PSC" orientacao="Sim            " />
        <bancada Sigla="Repr.PRONA" orientacao="Sim            " />
        <bancada Sigla="Repr.PTC" orientacao="Sim            " />
        <bancada Sigla="MINORIA" orientacao="Sim            " />
        <bancada Sigla="GOV." orientacao="Sim            " />
      </orientacaoBancada>
      <votos>
        <Deputado Nome="João Tota" ideCadastro="74240" Partido="PP        " UF="AC" Voto="Sim            " />
        <Deputado Nome="Zico Bronzeado" ideCadastro="73944" Partido="PT        " UF="AC" Voto="Sim            " />
        <Deputado Nome="Nilson Mourão" ideCadastro="74365" Partido="PT        " UF="AC" Voto="Sim            " />
        <Deputado Nome="Henrique Afonso" ideCadastro="73940" Partido="PT        " UF="AC" Voto="Sim            " />
        <Deputado Nome="João Correia" ideCadastro="73941" Partido="PMDB      " UF="AC" Voto="Sim            " />
        <Deputado Nome="Chicão Brígido" ideCadastro="74181" Partido="PMDB      " UF="AC" Voto="Sim            " />
        <Deputado Nome="Perpétua Almeida" ideCadastro="73943" Partido="PCdoB     " UF="AC" Voto="Sim            " />
        <Deputado Nome="Benedito de Lira" ideCadastro="74517" Partido="PP        " UF="AL" Voto="Sim            " />
        <Deputado Nome="João Lyra" ideCadastro="74049" Partido="PTB       " UF="AL" Voto="Sim            " />
        <Deputado Nome="Olavo Calheiros" ideCadastro="74005" Partido="PMDB      " UF="AL" Voto="Sim            " />
        <Deputado Nome="José Thomaz Nonô" ideCadastro="74520" Partido="PFL       " UF="AL" Voto="Sim            " />
        <Deputado Nome="Rogério Teófilo" ideCadastro="74051" Partido="PPS       " UF="AL" Voto="Sim            " />
        <Deputado Nome="Givaldo Carimbão" ideCadastro="74558" Partido="PSB       " UF="AL" Voto="Sim            " />
        <Deputado Nome="Maurício Quintella Lessa" ideCadastro="74050" Partido="PDT       " UF="AL" Voto="Sim            " />
        <Deputado Nome="Helenildo Ribeiro" ideCadastro="73582" Partido="PSDB      " UF="AL" Voto="Sim            " />
        <Deputado Nome="Silas Câmara" ideCadastro="74356" Partido="PTB       " UF="AM" Voto="Sim            " />
        <Deputado Nome="Carlos Souza" ideCadastro="73934" Partido="PP        " UF="AM" Voto="Sim            " />
        <Deputado Nome="Lupércio Ramos" ideCadastro="73936" Partido="PMDB      " UF="AM" Voto="Sim            " />
        <Deputado Nome="Francisco Garcia" ideCadastro="74355" Partido="PP        " UF="AM" Voto="Sim            " />
        <Deputado Nome="Vanessa Grazziotin" ideCadastro="74357" Partido="PCdoB     " UF="AM" Voto="Sim            " />
        <Deputado Nome="Hélio Esteves" ideCadastro="73925" Partido="PT        " UF="AP" Voto="Sim            " />
        <Deputado Nome="Eduardo Seabra" ideCadastro="74344" Partido="PTB       " UF="AP" Voto="Sim            " />
        <Deputado Nome="Evandro Milhomen" ideCadastro="74345" Partido="PCdoB     " UF="AP" Voto="Sim            " />
        <Deputado Nome="João Leão" ideCadastro="74550" Partido="PP        " UF="BA" Voto="Sim            " />
        <Deputado Nome="Severiano Alves" ideCadastro="74641" Partido="PDT       " UF="BA" Voto="Sim            " />
        <Deputado Nome="Walter Pinheiro" ideCadastro="74218" Partido="PT        " UF="BA" Voto="Sim            " />
        <Deputado Nome="Josias Gomes" ideCadastro="74141" Partido="PT        " UF="BA" Voto="Sim            " />
        <Deputado Nome="Guilherme Menezes" ideCadastro="74139" Partido="PT        " UF="BA" Voto="Sim            " />
        <Deputado Nome="Luiz Bassuma" ideCadastro="74059" Partido="PT        " UF="BA" Voto="Sim            " />
        <Deputado Nome="Nelson Pellegrino" ideCadastro="74571" Partido="PT        " UF="BA" Voto="Sim            " />
        <Deputado Nome="Félix Mendonça" ideCadastro="74542" Partido="PFL       " UF="BA" Voto="Sim            " />
        <Deputado Nome="Jonival Lucas Junior" ideCadastro="74568" Partido="PTB       " UF="BA" Voto="Sim            " />
        <Deputado Nome="Colbert Martins" ideCadastro="74230" Partido="PPS       " UF="BA" Voto="Sim            " />
        <Deputado Nome="José Carlos Araújo" ideCadastro="74140" Partido="PL        " UF="BA" Voto="Sim            " />
        <Deputado Nome="Reginaldo Germano" ideCadastro="73574" Partido="PP        " UF="BA" Voto="Sim            " />
        <Deputado Nome="Jairo Carneiro" ideCadastro="74547" Partido="PFL       " UF="BA" Voto="Sim            " />
        <Deputado Nome="Claudio Cajado" ideCadastro="74537" Partido="PFL       " UF="BA" Voto="Sim            " />
        <Deputado Nome="Paulo Magalhães" ideCadastro="74574" Partido="PFL       " UF="BA" Voto="Sim            " />
        <Deputado Nome="Aroldo Cedraz" ideCadastro="74534" Partido="PFL       " UF="BA" Voto="Sim            " />
        <Deputado Nome="José Carlos Aleluia" ideCadastro="74553" Partido="PFL       " UF="BA" Voto="Sim            " />
        <Deputado Nome="Marcelo Guimarães Filho" ideCadastro="74143" Partido="PFL       " UF="BA" Voto="Sim            " />
        <Deputado Nome="Zelinda Novaes" ideCadastro="74144" Partido="PFL       " UF="BA" Voto="Sim            " />
        <Deputado Nome="Edson Duarte" ideCadastro="74061" Partido="PV        " UF="BA" Voto="Sim            " />
        <Deputado Nome="Jutahy Junior" ideCadastro="74570" Partido="PSDB      " UF="BA" Voto="Sim            " />
        <Deputado Nome="Alice Portugal" ideCadastro="74057" Partido="PCdoB     " UF="BA" Voto="Sim            " />
        <Deputado Nome="José Linhares" ideCadastro="74297" Partido="PP        " UF="CE" Voto="Sim            " />
        <Deputado Nome="André Figueiredo" ideCadastro="133439" Partido="PDT       " UF="CE" Voto="Sim            " />
        <Deputado Nome="João Alfredo" ideCadastro="74031" Partido="PSOL      " UF="CE" Voto="Sim            " />
        <Deputado Nome="José Pimentel" ideCadastro="74298" Partido="PT        " UF="CE" Voto="Sim            " />
        <Deputado Nome="Gonzaga Mota" ideCadastro="74294" Partido="PSDB      " UF="CE" Voto="Sim            " />
        <Deputado Nome="Marcelo Teixeira" ideCadastro="74300" Partido="PSDB      " UF="CE" Voto="Sim            " />
        <Deputado Nome="Eunício Oliveira" ideCadastro="74454" Partido="PMDB      " UF="CE" Voto="Sim            " />
        <Deputado Nome="Zé Gerardo" ideCadastro="74309" Partido="PMDB      " UF="CE" Voto="Sim            " />
        <Deputado Nome="Almeida de Jesus" ideCadastro="74451" Partido="PL        " UF="CE" Voto="Sim            " />
        <Deputado Nome="Pastor Pedro Ribeiro" ideCadastro="74032" Partido="PMDB      " UF="CE" Voto="Sim            " />
        <Deputado Nome="Moroni Torgan" ideCadastro="74457" Partido="PFL       " UF="CE" Voto="Sim            " />
        <Deputado Nome="Léo Alcântara" ideCadastro="74455" Partido="PSDB      " UF="CE" Voto="Sim            " />
        <Deputado Nome="Raimundo Gomes de Matos" ideCadastro="74216" Partido="PSDB      " UF="CE" Voto="Sim            " />
        <Deputado Nome="Antonio Cambraia" ideCadastro="74452" Partido="PSDB      " UF="CE" Voto="Sim            " />
        <Deputado Nome="Manoel Salviano" ideCadastro="74456" Partido="PSDB      " UF="CE" Voto="Sim            " />
        <Deputado Nome="Ariosto Holanda" ideCadastro="74103" Partido="PSB       " UF="CE" Voto="Sim            " />
        <Deputado Nome="Inácio Arruda" ideCadastro="74295" Partido="PCdoB     " UF="CE" Voto="Sim            " />
        <Deputado Nome="Maninha" ideCadastro="74288" Partido="PSOL      " UF="DF" Voto="Sim            " />
        <Deputado Nome="Sigmaringa Seixas" ideCadastro="73718" Partido="PT        " UF="DF" Voto="Sim            " />
        <Deputado Nome="Alberto Fraga" ideCadastro="73579" Partido="PFL       " UF="DF" Voto="Sim            " />
        <Deputado Nome="Tadeu Filippelli" ideCadastro="74806" Partido="PMDB      " UF="DF" Voto="Sim            " />
        <Deputado Nome="Jorge Pinheiro" ideCadastro="73569" Partido="PL        " UF="DF" Voto="Sim            " />
        <Deputado Nome="Tatico" ideCadastro="74289" Partido="PTB       " UF="DF" Voto="Sim            " />
        <Deputado Nome="Jair de Oliveira" ideCadastro="133376" Partido="PMDB      " UF="ES" Voto="Sim            " />
        <Deputado Nome="Manato" ideCadastro="74163" Partido="PDT       " UF="ES" Voto="Sim            " />
        <Deputado Nome="Iriny Lopes" ideCadastro="74162" Partido="PT        " UF="ES" Voto="Sim            " />
        <Deputado Nome="Renato Casagrande" ideCadastro="74166" Partido="PSB       " UF="ES" Voto="Sim            " />
        <Deputado Nome="Ricardo Santos" ideCadastro="140241" Partido="PSDB      " UF="ES" Voto="Sim            " />
        <Deputado Nome="Feu Rosa" ideCadastro="74771" Partido="PP        " UF="ES" Voto="Sim            " />
        <Deputado Nome="Rose de Freitas" ideCadastro="73507" Partido="PMDB      " UF="ES" Voto="Sim            " />
        <Deputado Nome="Sandes Júnior" ideCadastro="74372" Partido="PP        " UF="GO" Voto="Sim            " />
        <Deputado Nome="Leonardo Vilela" ideCadastro="74368" Partido="PSDB      " UF="GO" Voto="Sim            " />
        <Deputado Nome="Neyde Aparecida" ideCadastro="74369" Partido="PT        " UF="GO" Voto="Sim            " />
        <Deputado Nome="Luiz Bittencourt" ideCadastro="74810" Partido="PMDB      " UF="GO" Voto="Sim            " />
        <Deputado Nome="Barbosa Neto" ideCadastro="73663" Partido="PSB       " UF="GO" Voto="Sim            " />
        <Deputado Nome="Pedro Chaves" ideCadastro="74812" Partido="PMDB      " UF="GO" Voto="Sim            " />
        <Deputado Nome="Sandro Mabel" ideCadastro="73676" Partido="PL        " UF="GO" Voto="Sim            " />
        <Deputado Nome="Vilmar Rocha" ideCadastro="73677" Partido="PFL       " UF="GO" Voto="Sim            " />
        <Deputado Nome="Carlos Alberto Leréia" ideCadastro="74290" Partido="PSDB      " UF="GO" Voto="Sim            " />
        <Deputado Nome="Jovair Arantes" ideCadastro="73666" Partido="PTB       " UF="GO" Voto="Sim            " />
        <Deputado Nome="Professora Raquel Teixeira" ideCadastro="74370" Partido="PSDB      " UF="GO" Voto="Sim            " />
        <Deputado Nome="Luciano Leitoa" ideCadastro="74028" Partido="PSB       " UF="MA" Voto="Sim            " />
        <Deputado Nome="Wagner Lago" ideCadastro="65551" Partido="PDT       " UF="MA" Voto="Sim            " />
        <Deputado Nome="Albérico Filho" ideCadastro="74018" Partido="PMDB      " UF="MA" Voto="Sim            " />
        <Deputado Nome="Pedro Novais" ideCadastro="74207" Partido="PMDB      " UF="MA" Voto="Sim            " />
        <Deputado Nome="Gastão Vieira" ideCadastro="74200" Partido="PMDB      " UF="MA" Voto="Sim            " />
        <Deputado Nome="Remi Trinta" ideCadastro="74208" Partido="PL        " UF="MA" Voto="Sim            " />
        <Deputado Nome="Nice Lobão" ideCadastro="74447" Partido="PFL       " UF="MA" Voto="Sim            " />
        <Deputado Nome="Costa Ferreira" ideCadastro="74016" Partido="PSC       " UF="MA" Voto="Sim            " />
        <Deputado Nome="Pedro Fernandes" ideCadastro="74449" Partido="PTB       " UF="MA" Voto="Sim            " />
        <Deputado Nome="Dr. Ribamar Alves" ideCadastro="74027" Partido="PSB       " UF="MA" Voto="Sim            " />
        <Deputado Nome="João Castelo" ideCadastro="74445" Partido="PSDB      " UF="MA" Voto="Sim            " />
        <Deputado Nome="Herculano Anghinetti" ideCadastro="74660" Partido="PP        " UF="MG" Voto="Sim            " />
        <Deputado Nome="Márcio Reinaldo Moreira" ideCadastro="74744" Partido="PP        " UF="MG" Voto="Sim            " />
        <Deputado Nome="Mário Heringer" ideCadastro="74158" Partido="PDT       " UF="MG" Voto="Sim            " />
        <Deputado Nome="Maria do Carmo Lara" ideCadastro="74586" Partido="PT        " UF="MG" Voto="Sim            " />
        <Deputado Nome="Odair Cunha" ideCadastro="74159" Partido="PT        " UF="MG" Voto="Sim            " />
        <Deputado Nome="Virgílio Guimarães" ideCadastro="74593" Partido="PT        " UF="MG" Voto="Sim            " />
        <Deputado Nome="Reginaldo Lopes" ideCadastro="74161" Partido="PT        " UF="MG" Voto="Sim            " />
        <Deputado Nome="Paulo Delgado" ideCadastro="74754" Partido="PT        " UF="MG" Voto="Sim            " />
        <Deputado Nome="Vadinho Baião" ideCadastro="74494" Partido="PT        " UF="MG" Voto="Sim            " />
        <Deputado Nome="Ana Guerra" ideCadastro="134115" Partido="PT        " UF="MG" Voto="Sim            " />
        <Deputado Nome="Gilmar Machado" ideCadastro="74581" Partido="PT        " UF="MG" Voto="Sim            " />
        <Deputado Nome="Leonardo Monteiro" ideCadastro="74156" Partido="PT        " UF="MG" Voto="Sim            " />
        <Deputado Nome="César Medeiros" ideCadastro="74149" Partido="PT        " UF="MG" Voto="Sim            " />
        <Deputado Nome="Romeu Queiroz" ideCadastro="74591" Partido="PTB       " UF="MG" Voto="Sim            " />
        <Deputado Nome="José Militão" ideCadastro="74584" Partido="PTB       " UF="MG" Voto="Sim            " />
        <Deputado Nome="Mauro Lopes" ideCadastro="74749" Partido="PMDB      " UF="MG" Voto="Sim            " />
        <Deputado Nome="João Magalhães" ideCadastro="74120" Partido="PMDB      " UF="MG" Voto="Sim            " />
        <Deputado Nome="Marcello Siqueira" ideCadastro="74157" Partido="PMDB      " UF="MG" Voto="Sim            " />
        <Deputado Nome="Fernando Diniz" ideCadastro="74658" Partido="PMDB      " UF="MG" Voto="Sim            " />
        <Deputado Nome="Saraiva Felipe" ideCadastro="74762" Partido="PMDB      " UF="MG" Voto="Sim            " />
        <Deputado Nome="Lincoln Portela" ideCadastro="74585" Partido="PL        " UF="MG" Voto="Sim            " />
        <Deputado Nome="Carlos Willian" ideCadastro="74148" Partido="PTC       " UF="MG" Voto="Sim            " />
        <Deputado Nome="Carlos Mota" ideCadastro="74484" Partido="PSB       " UF="MG" Voto="Sim            " />
        <Deputado Nome="Mário Assad Júnior" ideCadastro="74329" Partido="PSB       " UF="MG" Voto="Sim            " />
        <Deputado Nome="Júlio Delgado" ideCadastro="73586" Partido="PSB       " UF="MG" Voto="Sim            " />
        <Deputado Nome="Geraldo Thadeu" ideCadastro="74151" Partido="PPS       " UF="MG" Voto="Sim            " />
        <Deputado Nome="José Santana de Vasconcellos" ideCadastro="74741" Partido="PL        " UF="MG" Voto="Sim            " />
        <Deputado Nome="Eliseu Resende" ideCadastro="74657" Partido="PFL       " UF="MG" Voto="Sim            " />
        <Deputado Nome="Jaime Martins" ideCadastro="74665" Partido="PL        " UF="MG" Voto="Sim            " />
        <Deputado Nome="Carlos Melles" ideCadastro="74651" Partido="PFL       " UF="MG" Voto="Sim            " />
        <Deputado Nome="Isaías Silvestre" ideCadastro="74152" Partido="PSB       " UF="MG" Voto="Sim            " />
        <Deputado Nome="Leonardo Mattos" ideCadastro="74155" Partido="PV        " UF="MG" Voto="Sim            " />
        <Deputado Nome="Narcio Rodrigues" ideCadastro="74108" Partido="PSDB      " UF="MG" Voto="Sim            " />
        <Deputado Nome="Eduardo Barbosa" ideCadastro="74655" Partido="PSDB      " UF="MG" Voto="Sim            " />
        <Deputado Nome="Custódio Mattos" ideCadastro="74579" Partido="PSDB      " UF="MG" Voto="Sim            " />
        <Deputado Nome="Rafael Guerra" ideCadastro="74590" Partido="PSDB      " UF="MG" Voto="Sim            " />
        <Deputado Nome="Sérgio Miranda" ideCadastro="74763" Partido="PDT       " UF="MG" Voto="Sim            " />
        <Deputado Nome="João Grandão" ideCadastro="73454" Partido="PT        " UF="MS" Voto="Sim            " />
        <Deputado Nome="Antônio Carlos Biffi" ideCadastro="74373" Partido="PT        " UF="MS" Voto="Sim            " />
        <Deputado Nome="Vander Loubet" ideCadastro="74376" Partido="PT        " UF="MS" Voto="Sim            " />
        <Deputado Nome="Nelson Trad" ideCadastro="73761" Partido="PMDB      " UF="MS" Voto="Sim            " />
        <Deputado Nome="Waldemir Moka" ideCadastro="73456" Partido="PMDB      " UF="MS" Voto="Sim            " />
        <Deputado Nome="Antonio Cruz" ideCadastro="73817" Partido="PP        " UF="MS" Voto="Sim            " />
        <Deputado Nome="Geraldo Resende" ideCadastro="74374" Partido="PPS       " UF="MS" Voto="Sim            " />
        <Deputado Nome="Pedro Henry" ideCadastro="74111" Partido="PP        " UF="MT" Voto="Sim            " />
        <Deputado Nome="Carlos Abicalil" ideCadastro="74285" Partido="PT        " UF="MT" Voto="Sim            " />
        <Deputado Nome="Teté Bezerra" ideCadastro="73652" Partido="PMDB      " UF="MT" Voto="Sim            " />
        <Deputado Nome="Wellington Fagundes" ideCadastro="73653" Partido="PL        " UF="MT" Voto="Sim            " />
        <Deputado Nome="Celcita Pinheiro" ideCadastro="74799" Partido="PFL       " UF="MT" Voto="Sim            " />
        <Deputado Nome="Thelma de Oliveira" ideCadastro="74286" Partido="PSDB      " UF="MT" Voto="Sim            " />
        <Deputado Nome="Zé Lima" ideCadastro="73932" Partido="PP        " UF="PA" Voto="Sim            " />
        <Deputado Nome="Babá" ideCadastro="74349" Partido="PSOL      " UF="PA" Voto="Sim            " />
        <Deputado Nome="Zé Geraldo" ideCadastro="73931" Partido="PT        " UF="PA" Voto="Sim            " />
        <Deputado Nome="Josué Bengtson" ideCadastro="74351" Partido="PTB       " UF="PA" Voto="Sim            " />
        <Deputado Nome="Ann Pontes" ideCadastro="73928" Partido="PMDB      " UF="PA" Voto="Sim            " />
        <Deputado Nome="Asdrubal Bentes" ideCadastro="74222" Partido="PMDB      " UF="PA" Voto="Sim            " />
        <Deputado Nome="José Priante" ideCadastro="74079" Partido="PMDB      " UF="PA" Voto="Sim            " />
        <Deputado Nome="Raimundo Santos" ideCadastro="74084" Partido="PL        " UF="PA" Voto="Sim            " />
        <Deputado Nome="Vic Pires Franco" ideCadastro="74087" Partido="PFL       " UF="PA" Voto="Sim            " />
        <Deputado Nome="Anivaldo Vale" ideCadastro="74072" Partido="PSDB      " UF="PA" Voto="Sim            " />
        <Deputado Nome="Zenaldo Coutinho" ideCadastro="74354" Partido="PSDB      " UF="PA" Voto="Sim            " />
        <Deputado Nome="Nilson Pinto" ideCadastro="74352" Partido="PSDB      " UF="PA" Voto="Sim            " />
        <Deputado Nome="Socorro Gomes" ideCadastro="74085" Partido="PCdoB     " UF="PA" Voto="Sim            " />
        <Deputado Nome="Luiz Couto" ideCadastro="74041" Partido="PT        " UF="PB" Voto="Sim            " />
        <Deputado Nome="Carlos Dunga" ideCadastro="74466" Partido="PTB       " UF="PB" Voto="Sim            " />
        <Deputado Nome="Wellington Roberto" ideCadastro="74043" Partido="PL        " UF="PB" Voto="Sim            " />
        <Deputado Nome="Wilson Santiago" ideCadastro="74044" Partido="PMDB      " UF="PB" Voto="Sim            " />
        <Deputado Nome="Philemon Rodrigues" ideCadastro="74756" Partido="PTB       " UF="PB" Voto="Sim            " />
        <Deputado Nome="Marcondes Gadelha" ideCadastro="74470" Partido="PSB       " UF="PB" Voto="Sim            " />
        <Deputado Nome="Lúcia Braga" ideCadastro="65987" Partido="PMDB      " UF="PB" Voto="Sim            " />
        <Deputado Nome="Domiciano Cabral" ideCadastro="74468" Partido="PSDB      " UF="PB" Voto="Sim            " />
        <Deputado Nome="Maurício Rands" ideCadastro="74045" Partido="PT        " UF="PE" Voto="Sim            " />
        <Deputado Nome="Fernando Ferro" ideCadastro="74417" Partido="PT        " UF="PE" Voto="Sim            " />
        <Deputado Nome="Armando Monteiro" ideCadastro="74472" Partido="PTB       " UF="PE" Voto="Sim            " />
        <Deputado Nome="Carlos Eduardo Cadoca" ideCadastro="74474" Partido="PMDB      " UF="PE" Voto="Sim            " />
        <Deputado Nome="Salatiel Carvalho" ideCadastro="74434" Partido="PFL       " UF="PE" Voto="Sim            " />
        <Deputado Nome="André de Paula" ideCadastro="74471" Partido="PFL       " UF="PE" Voto="Sim            " />
        <Deputado Nome="Inocêncio Oliveira" ideCadastro="74421" Partido="PL        " UF="PE" Voto="Sim            " />
        <Deputado Nome="Joel de Hollanda" ideCadastro="73575" Partido="PFL       " UF="PE" Voto="Sim            " />
        <Deputado Nome="Joaquim Francisco" ideCadastro="74477" Partido="PFL       " UF="PE" Voto="Sim            " />
        <Deputado Nome="Jorge Gomes" ideCadastro="74495" Partido="PSB       " UF="PE" Voto="Sim            " />
        <Deputado Nome="Pastor Francisco Olímpio" ideCadastro="74046" Partido="PSB       " UF="PE" Voto="Sim            " />
        <Deputado Nome="Luiz Piauhylino" ideCadastro="74427" Partido="PDT       " UF="PE" Voto="Sim            " />
        <Deputado Nome="Roberto Magalhães" ideCadastro="74433" Partido="PFL       " UF="PE" Voto="Sim            " />
        <Deputado Nome="José Múcio Monteiro" ideCadastro="74426" Partido="PTB       " UF="PE" Voto="Sim            " />
        <Deputado Nome="Renildo Calheiros" ideCadastro="73801" Partido="PCdoB     " UF="PE" Voto="Sim            " />
        <Deputado Nome="Nazareno Fonteles" ideCadastro="74491" Partido="PT        " UF="PI" Voto="Sim            " />
        <Deputado Nome="Simplício Mário" ideCadastro="74492" Partido="PT        " UF="PI" Voto="Sim            " />
        <Deputado Nome="Moraes Souza" ideCadastro="74034" Partido="PMDB      " UF="PI" Voto="Sim            " />
        <Deputado Nome="Marcelo Castro" ideCadastro="74460" Partido="PMDB      " UF="PI" Voto="Sim            " />
        <Deputado Nome="Júlio Cesar" ideCadastro="74317" Partido="PFL       " UF="PI" Voto="Sim            " />
        <Deputado Nome="Átila Lira" ideCadastro="74459" Partido="PSDB      " UF="PI" Voto="Sim            " />
        <Deputado Nome="Nelson Meurer" ideCadastro="73781" Partido="PP        " UF="PR" Voto="Sim            " />
        <Deputado Nome="Ricardo Barros" ideCadastro="73788" Partido="PP        " UF="PR" Voto="Sim            " />
        <Deputado Nome="Colombo" ideCadastro="74380" Partido="PT        " UF="PR" Voto="Sim            " />
        <Deputado Nome="Dr. Rosinha" ideCadastro="73459" Partido="PT        " UF="PR" Voto="Sim            " />
        <Deputado Nome="Assis Miguel do Couto" ideCadastro="74378" Partido="PT        " UF="PR" Voto="Sim            " />
        <Deputado Nome="Selma Schons" ideCadastro="74403" Partido="PT        " UF="PR" Voto="Sim            " />
        <Deputado Nome="Vitorassi" ideCadastro="134893" Partido="PT        " UF="PR" Voto="Sim            " />
        <Deputado Nome="Dra. Clair" ideCadastro="74381" Partido="PT        " UF="PR" Voto="Sim            " />
        <Deputado Nome="Takayama" ideCadastro="74385" Partido="PMDB      " UF="PR" Voto="Sim            " />
        <Deputado Nome="Iris Simões" ideCadastro="73461" Partido="PTB       " UF="PR" Voto="Sim            " />
        <Deputado Nome="Airton Roveda" ideCadastro="73457" Partido="PPS       " UF="PR" Voto="Sim            " />
        <Deputado Nome="Moacir Micheletto" ideCadastro="74238" Partido="PMDB      " UF="PR" Voto="Sim            " />
        <Deputado Nome="Osmar Serraglio" ideCadastro="73463" Partido="PMDB      " UF="PR" Voto="Sim            " />
        <Deputado Nome="Hermes Parcianello" ideCadastro="73772" Partido="PMDB      " UF="PR" Voto="Sim            " />
        <Deputado Nome="Gustavo Fruet" ideCadastro="73460" Partido="PSDB      " UF="PR" Voto="Sim            " />
        <Deputado Nome="Cezar Silvestri" ideCadastro="74379" Partido="PPS       " UF="PR" Voto="Sim            " />
        <Deputado Nome="Abelardo Lupion" ideCadastro="73764" Partido="PFL       " UF="PR" Voto="Sim            " />
        <Deputado Nome="Eduardo Sciarra" ideCadastro="74382" Partido="PFL       " UF="PR" Voto="Sim            " />
        <Deputado Nome="Luiz Carlos Hauly" ideCadastro="73778" Partido="PSDB      " UF="PR" Voto="Sim            " />
        <Deputado Nome="Affonso Camargo" ideCadastro="73765" Partido="PSDB      " UF="PR" Voto="Sim            " />
        <Deputado Nome="Chico da Princesa" ideCadastro="74000" Partido="PL        " UF="PR" Voto="Sim            " />
        <Deputado Nome="Alex Canziani" ideCadastro="73458" Partido="PTB       " UF="PR" Voto="Sim            " />
        <Deputado Nome="Odílio Balbinotti" ideCadastro="73782" Partido="PMDB      " UF="PR" Voto="Sim            " />
        <Deputado Nome="Jair Bolsonaro" ideCadastro="74847" Partido="PP        " UF="RJ" Voto="Sim            " />
        <Deputado Nome="Simão Sessim" ideCadastro="73424" Partido="PP        " UF="RJ" Voto="Sim            " />
        <Deputado Nome="Eduardo Cunha" ideCadastro="74173" Partido="PMDB      " UF="RJ" Voto="Sim            " />
        <Deputado Nome="Almerinda de Carvalho" ideCadastro="74675" Partido="PMDB      " UF="RJ" Voto="Sim            " />
        <Deputado Nome="Miro Teixeira" ideCadastro="74862" Partido="PDT       " UF="RJ" Voto="Sim            " />
        <Deputado Nome="Elaine Costa" ideCadastro="74174" Partido="PTB       " UF="RJ" Voto="Sim            " />
        <Deputado Nome="Chico Alencar" ideCadastro="74171" Partido="PSOL      " UF="RJ" Voto="Sim            " />
        <Deputado Nome="Luiz Sérgio" ideCadastro="74688" Partido="PT        " UF="RJ" Voto="Sim            " />
        <Deputado Nome="Fernando Gabeira" ideCadastro="74841" Partido="PV        " UF="RJ" Voto="Sim            " />
        <Deputado Nome="Jorge Bittar" ideCadastro="74686" Partido="PT        " UF="RJ" Voto="Sim            " />
        <Deputado Nome="Antonio Carlos Biscaia" ideCadastro="73492" Partido="PT        " UF="RJ" Voto="Sim            " />
        <Deputado Nome="Moreira Franco" ideCadastro="74863" Partido="PMDB      " UF="RJ" Voto="Sim            " />
        <Deputado Nome="Vieira Reis" ideCadastro="74259" Partido="S.Part.   " UF="RJ" Voto="Sim            " />
        <Deputado Nome="Leonardo Picciani" ideCadastro="74254" Partido="PMDB      " UF="RJ" Voto="Sim            " />
        <Deputado Nome="Nelson Bornier" ideCadastro="73416" Partido="PMDB      " UF="RJ" Voto="Sim            " />
        <Deputado Nome="Aldir Cabral" ideCadastro="74828" Partido="PFL       " UF="RJ" Voto="Sim            " />
        <Deputado Nome="Eduardo Paes" ideCadastro="74683" Partido="PSDB      " UF="RJ" Voto="Sim            " />
        <Deputado Nome="Laura Carneiro" ideCadastro="74856" Partido="PFL       " UF="RJ" Voto="Sim            " />
        <Deputado Nome="Josias Quintal" ideCadastro="74176" Partido="PSB       " UF="RJ" Voto="Sim            " />
        <Deputado Nome="Edson Ezequiel" ideCadastro="74838" Partido="PMDB      " UF="RJ" Voto="Sim            " />
        <Deputado Nome="Fernando Lopes" ideCadastro="74843" Partido="PMDB      " UF="RJ" Voto="Sim            " />
        <Deputado Nome="Sandro Matos" ideCadastro="74258" Partido="PTB       " UF="RJ" Voto="Sim            " />
        <Deputado Nome="Deley" ideCadastro="74172" Partido="PSC       " UF="RJ" Voto="Sim            " />
        <Deputado Nome="Alexandre Santos" ideCadastro="74830" Partido="PMDB      " UF="RJ" Voto="Sim            " />
        <Deputado Nome="Paulo Feijó" ideCadastro="74017" Partido="PSDB      " UF="RJ" Voto="Sim            " />
        <Deputado Nome="Ronaldo Cezar Coelho" ideCadastro="73421" Partido="PSDB      " UF="RJ" Voto="Sim            " />
        <Deputado Nome="Dr. Heleno" ideCadastro="74680" Partido="PSC       " UF="RJ" Voto="Sim            " />
        <Deputado Nome="Jandira Feghali" ideCadastro="74848" Partido="PCdoB     " UF="RJ" Voto="Sim            " />
        <Deputado Nome="Henrique Eduardo Alves" ideCadastro="74324" Partido="PMDB      " UF="RN" Voto="Sim            " />
        <Deputado Nome="Anselmo" ideCadastro="73937" Partido="PT        " UF="RO" Voto="Sim            " />
        <Deputado Nome="Eduardo Valverde" ideCadastro="73938" Partido="PT        " UF="RO" Voto="Sim            " />
        <Deputado Nome="Marinha Raupp" ideCadastro="74177" Partido="PMDB      " UF="RO" Voto="Sim            " />
        <Deputado Nome="Natan Donadon" ideCadastro="133372" Partido="PMDB      " UF="RO" Voto="Sim            " />
        <Deputado Nome="Agnaldo Muniz" ideCadastro="74358" Partido="PP        " UF="RO" Voto="Sim            " />
        <Deputado Nome="Miguel de Souza" ideCadastro="73939" Partido="PL        " UF="RO" Voto="Sim            " />
        <Deputado Nome="Almir Sá" ideCadastro="74341" Partido="PL        " UF="RR" Voto="Sim            " />
        <Deputado Nome="Pastor Frankembergen" ideCadastro="73921" Partido="PTB       " UF="RR" Voto="Sim            " />
        <Deputado Nome="Dr. Rodolfo Pereira" ideCadastro="73920" Partido="PDT       " UF="RR" Voto="Sim            " />
        <Deputado Nome="Maria Helena" ideCadastro="64960" Partido="PSB       " UF="RR" Voto="Sim            " />
        <Deputado Nome="Francisco Rodrigues" ideCadastro="73981" Partido="PFL       " UF="RR" Voto="Sim            " />
        <Deputado Nome="Suely Campos" ideCadastro="73922" Partido="PP        " UF="RR" Voto="Sim            " />
        <Deputado Nome="Érico Ribeiro" ideCadastro="74393" Partido="PP        " UF="RS" Voto="Sim            " />
        <Deputado Nome="Luis Carlos Heinze" ideCadastro="73483" Partido="PP        " UF="RS" Voto="Sim            " />
        <Deputado Nome="Pompeo de Mattos" ideCadastro="73486" Partido="PDT       " UF="RS" Voto="Sim            " />
        <Deputado Nome="Tarcísio Zimmermann" ideCadastro="73577" Partido="PT        " UF="RS" Voto="Sim            " />
        <Deputado Nome="Paulo Pimenta" ideCadastro="74400" Partido="PT        " UF="RS" Voto="Sim            " />
        <Deputado Nome="Marco Maia" ideCadastro="133373" Partido="PT        " UF="RS" Voto="Sim            " />
        <Deputado Nome="Orlando Desconsi" ideCadastro="73684" Partido="PT        " UF="RS" Voto="Sim            " />
        <Deputado Nome="Adão Pretto" ideCadastro="73886" Partido="PT        " UF="RS" Voto="Sim            " />
        <Deputado Nome="Maria do Rosário" ideCadastro="74398" Partido="PT        " UF="RS" Voto="Sim            " />
        <Deputado Nome="Luciana Genro" ideCadastro="74397" Partido="PSOL      " UF="RS" Voto="Sim            " />
        <Deputado Nome="Pastor Reinaldo" ideCadastro="62926" Partido="PTB       " UF="RS" Voto="Sim            " />
        <Deputado Nome="Edir Oliveira" ideCadastro="73599" Partido="PTB       " UF="RS" Voto="Sim            " />
        <Deputado Nome="Darcísio Perondi" ideCadastro="73891" Partido="PMDB      " UF="RS" Voto="Sim            " />
        <Deputado Nome="Mendes Ribeiro Filho" ideCadastro="73904" Partido="PMDB      " UF="RS" Voto="Sim            " />
        <Deputado Nome="Eliseu Padilha" ideCadastro="73892" Partido="PMDB      " UF="RS" Voto="Sim            " />
        <Deputado Nome="Beto Albuquerque" ideCadastro="73478" Partido="PSB       " UF="RS" Voto="Sim            " />
        <Deputado Nome="João Pizzolatti" ideCadastro="73874" Partido="PP        " UF="SC" Voto="Sim            " />
        <Deputado Nome="Leodegar Tiscoski" ideCadastro="73473" Partido="PP        " UF="SC" Voto="Sim            " />
        <Deputado Nome="Ivan Ranzolin" ideCadastro="74387" Partido="PFL       " UF="SC" Voto="Sim            " />
        <Deputado Nome="Fernando Coruja" ideCadastro="73471" Partido="PPS       " UF="SC" Voto="Sim            " />
        <Deputado Nome="Jorge Boeira" ideCadastro="74388" Partido="PT        " UF="SC" Voto="Sim            " />
        <Deputado Nome="Carlito Merss" ideCadastro="73469" Partido="PT        " UF="SC" Voto="Sim            " />
        <Deputado Nome="Vignatti" ideCadastro="74391" Partido="PT        " UF="SC" Voto="Sim            " />
        <Deputado Nome="Edinho Bez" ideCadastro="73793" Partido="PMDB      " UF="SC" Voto="Sim            " />
        <Deputado Nome="Paulo Afonso" ideCadastro="74390" Partido="PMDB      " UF="SC" Voto="Sim            " />
        <Deputado Nome="João Matos" ideCadastro="73873" Partido="PMDB      " UF="SC" Voto="Sim            " />
        <Deputado Nome="Gervásio Silva" ideCadastro="73472" Partido="PFL       " UF="SC" Voto="Sim            " />
        <Deputado Nome="João Fontes" ideCadastro="74054" Partido="PDT       " UF="SE" Voto="Sim            " />
        <Deputado Nome="José Carlos Machado" ideCadastro="74055" Partido="PFL       " UF="SE" Voto="Sim            " />
        <Deputado Nome="Jackson Barreto" ideCadastro="77701" Partido="PTB       " UF="SE" Voto="Sim            " />
        <Deputado Nome="Bosco Costa" ideCadastro="74052" Partido="PSDB      " UF="SE" Voto="Sim            " />
        <Deputado Nome="José Eduardo Cardozo" ideCadastro="74274" Partido="PT        " UF="SP" Voto="Sim            " />
        <Deputado Nome="Telma de Souza" ideCadastro="73561" Partido="PT        " UF="SP" Voto="Sim            " />
        <Deputado Nome="Iara Bernardi" ideCadastro="74780" Partido="PT        " UF="SP" Voto="Sim            " />
        <Deputado Nome="Angela Guadagnin" ideCadastro="74699" Partido="PT        " UF="SP" Voto="Sim            " />
        <Deputado Nome="Arlindo Chinaglia" ideCadastro="73433" Partido="PT        " UF="SP" Voto="Sim            " />
        <Deputado Nome="João Paulo Cunha" ideCadastro="73534" Partido="PT        " UF="SP" Voto="Sim            " />
        <Deputado Nome="Ivan Valente" ideCadastro="73531" Partido="PSOL      " UF="SP" Voto="Sim            " />
        <Deputado Nome="José Mentor" ideCadastro="74275" Partido="PT        " UF="SP" Voto="Sim            " />
        <Deputado Nome="Orlando Fantazzini" ideCadastro="73603" Partido="PSOL      " UF="SP" Voto="Sim            " />
        <Deputado Nome="Luiz Eduardo Greenhalgh" ideCadastro="74137" Partido="PT        " UF="SP" Voto="Sim            " />
        <Deputado Nome="Professor Luizinho" ideCadastro="74792" Partido="PT        " UF="SP" Voto="Sim            " />
        <Deputado Nome="Durval Orlato" ideCadastro="74266" Partido="PT        " UF="SP" Voto="Sim            " />
        <Deputado Nome="Devanir Ribeiro" ideCadastro="74264" Partido="PT        " UF="SP" Voto="Sim            " />
        <Deputado Nome="Vicentinho" ideCadastro="74283" Partido="PT        " UF="SP" Voto="Sim            " />
        <Deputado Nome="Ricardo Izar" ideCadastro="73557" Partido="PTB       " UF="SP" Voto="Sim            " />
        <Deputado Nome="Fleury" ideCadastro="74700" Partido="PTB       " UF="SP" Voto="Sim            " />
        <Deputado Nome="Ary Kara" ideCadastro="73435" Partido="PTB       " UF="SP" Voto="Sim            " />
        <Deputado Nome="Edna Macedo" ideCadastro="74267" Partido="PTB       " UF="SP" Voto="Sim            " />
        <Deputado Nome="Arnaldo Faria de Sá" ideCadastro="73434" Partido="PTB       " UF="SP" Voto="Sim            " />
        <Deputado Nome="Paulo Lima" ideCadastro="73555" Partido="PMDB      " UF="SP" Voto="Sim            " />
        <Deputado Nome="Milton Monti" ideCadastro="74787" Partido="PL        " UF="SP" Voto="Sim            " />
        <Deputado Nome="Wanderval Santos" ideCadastro="74702" Partido="PL        " UF="SP" Voto="Sim            " />
        <Deputado Nome="Cláudio Magrão" ideCadastro="74263" Partido="PPS       " UF="SP" Voto="Sim            " />
        <Deputado Nome="Neuton Lima" ideCadastro="74790" Partido="PTB       " UF="SP" Voto="Sim            " />
        <Deputado Nome="João Batista" ideCadastro="74261" Partido="PP        " UF="SP" Voto="Sim            " />
        <Deputado Nome="Luiza Erundina" ideCadastro="74784" Partido="PSB       " UF="SP" Voto="Sim            " />
        <Deputado Nome="Gilberto Nascimento" ideCadastro="74270" Partido="PMDB      " UF="SP" Voto="Sim            " />
        <Deputado Nome="Jovino Cândido" ideCadastro="74276" Partido="PV        " UF="SP" Voto="Sim            " />
        <Deputado Nome="Marcelo Ortiz" ideCadastro="74278" Partido="PV        " UF="SP" Voto="Sim            " />
        <Deputado Nome="Carlos Sampaio" ideCadastro="74262" Partido="PSDB      " UF="SP" Voto="Sim            " />
        <Deputado Nome="Xico Graziano" ideCadastro="74797" Partido="PSDB      " UF="SP" Voto="Sim            " />
        <Deputado Nome="Lobbe Neto" ideCadastro="74277" Partido="PSDB      " UF="SP" Voto="Sim            " />
        <Deputado Nome="Walter Barelli" ideCadastro="133370" Partido="PSDB      " UF="SP" Voto="Sim            " />
        <Deputado Nome="Antonio Carlos Pannunzio" ideCadastro="73431" Partido="PSDB      " UF="SP" Voto="Sim            " />
        <Deputado Nome="Julio Semeghini" ideCadastro="74783" Partido="PSDB      " UF="SP" Voto="Sim            " />
        <Deputado Nome="Walter Feldman" ideCadastro="74284" Partido="PSDB      " UF="SP" Voto="Sim            " />
        <Deputado Nome="Antonio Carlos Mendes Thame" ideCadastro="73584" Partido="PSDB      " UF="SP" Voto="Sim            " />
        <Deputado Nome="Elimar Máximo Damasceno" ideCadastro="74268" Partido="PRONA     " UF="SP" Voto="Sim            " />
        <Deputado Nome="Amauri Gasques" ideCadastro="74260" Partido="PL        " UF="SP" Voto="Sim            " />
        <Deputado Nome="Ildeu Araujo" ideCadastro="74271" Partido="PP        " UF="SP" Voto="Sim            " />
        <Deputado Nome="Jamil Murad" ideCadastro="74272" Partido="PCdoB     " UF="SP" Voto="Sim            " />
        <Deputado Nome="Aldo Rebelo" ideCadastro="73428" Partido="PCdoB     " UF="SP" Voto="Art. 17        " />
        <Deputado Nome="Osvaldo Reis" ideCadastro="74191" Partido="PMDB      " UF="TO" Voto="Sim            " />
        <Deputado Nome="Darci Coelho" ideCadastro="74187" Partido="PP        " UF="TO" Voto="Sim            " />
        <Deputado Nome="Homero Barreto" ideCadastro="73946" Partido="PTB       " UF="TO" Voto="Sim            " />
        <Deputado Nome="Kátia Abreu" ideCadastro="73592" Partido="PFL       " UF="TO" Voto="Sim            " />
        <Deputado Nome="Ronaldo Dimas" ideCadastro="73948" Partido="PSDB      " UF="TO" Voto="Sim            " />
      </votos>
    </Votacao>
    <Votacao Resumo="Aprovado o Substitutivo do Senado Federal ao Projeto de Lei Complementar nº 184, de 2004. Sim: 371; Não: 0; Abstenção: 1; Total: 372." Data="10/12/2008" Hora="11:57" ObjVotacao="SUBSTITUTIVO DO SENADO FEDERAL" codSessao="3606">
      <orientacaoBancada>
        <bancada Sigla="PmdbPtc" orientacao="Sim            " />
        <bancada Sigla="PT" orientacao="Sim            " />
        <bancada Sigla="PsbPdtPCdoBPmnPrb" orientacao="Sim            " />
        <bancada Sigla="PSDB" orientacao="Sim            " />
        <bancada Sigla="DEM" orientacao="Sim            " />
        <bancada Sigla="PR" orientacao="Sim            " />
        <bancada Sigla="PP" orientacao="Sim            " />
        <bancada Sigla="PTB" orientacao="Sim            " />
        <bancada Sigla="PV" orientacao="Sim            " />
        <bancada Sigla="PPS" orientacao="Sim            " />
        <bancada Sigla="PSC" orientacao="Sim            " />
        <bancada Sigla="PSOL" orientacao="Sim            " />
        <bancada Sigla="MINORIA" orientacao="Sim            " />
        <bancada Sigla="GOV." orientacao="Sim            " />
      </orientacaoBancada>
      <votos>
        <Deputado Nome="Henrique Afonso" ideCadastro="73940" Partido="PT        " UF="AC" Voto="Sim            " />
        <Deputado Nome="Perpétua Almeida" ideCadastro="73943" Partido="PCdoB     " UF="AC" Voto="Sim            " />
        <Deputado Nome="Benedito de Lira" ideCadastro="74517" Partido="PP        " UF="AL" Voto="Sim            " />
        <Deputado Nome="Olavo Calheiros" ideCadastro="74005" Partido="PMDB      " UF="AL" Voto="Sim            " />
        <Deputado Nome="Givaldo Carimbão" ideCadastro="74558" Partido="PSB       " UF="AL" Voto="Sim            " />
        <Deputado Nome="Maurício Quintella Lessa" ideCadastro="74050" Partido="PR        " UF="AL" Voto="Sim            " />
        <Deputado Nome="Silas Câmara" ideCadastro="74356" Partido="PSC       " UF="AM" Voto="Sim            " />
        <Deputado Nome="Carlos Souza" ideCadastro="73934" Partido="PP        " UF="AM" Voto="Sim            " />
        <Deputado Nome="Átila Lins" ideCadastro="74090" Partido="PMDB      " UF="AM" Voto="Sim            " />
        <Deputado Nome="Vanessa Grazziotin" ideCadastro="74357" Partido="PCdoB     " UF="AM" Voto="Sim            " />
        <Deputado Nome="Davi Alcolumbre" ideCadastro="73924" Partido="DEM       " UF="AP" Voto="Sim            " />
        <Deputado Nome="Jurandil Juarez" ideCadastro="74346" Partido="PMDB      " UF="AP" Voto="Sim            " />
        <Deputado Nome="Janete Capiberibe" ideCadastro="73926" Partido="PSB       " UF="AP" Voto="Sim            " />
        <Deputado Nome="Evandro Milhomen" ideCadastro="74345" Partido="PCdoB     " UF="AP" Voto="Sim            " />
        <Deputado Nome="João Leão" ideCadastro="74550" Partido="PP        " UF="BA" Voto="Sim            " />
        <Deputado Nome="Severiano Alves" ideCadastro="74641" Partido="PDT       " UF="BA" Voto="Sim            " />
        <Deputado Nome="Luiz Alberto" ideCadastro="74133" Partido="PT        " UF="BA" Voto="Sim            " />
        <Deputado Nome="Walter Pinheiro" ideCadastro="74218" Partido="PT        " UF="BA" Voto="Sim            " />
        <Deputado Nome="Zezéu Ribeiro" ideCadastro="74145" Partido="PT        " UF="BA" Voto="Sim            " />
        <Deputado Nome="Guilherme Menezes" ideCadastro="74139" Partido="PT        " UF="BA" Voto="Sim            " />
        <Deputado Nome="Luiz Bassuma" ideCadastro="74059" Partido="PT        " UF="BA" Voto="Sim            " />
        <Deputado Nome="Nelson Pellegrino" ideCadastro="74571" Partido="PT        " UF="BA" Voto="Sim            " />
        <Deputado Nome="Colbert Martins" ideCadastro="74230" Partido="PMDB      " UF="BA" Voto="Sim            " />
        <Deputado Nome="José Carlos Araújo" ideCadastro="74140" Partido="PR        " UF="BA" Voto="Sim            " />
        <Deputado Nome="Claudio Cajado" ideCadastro="74537" Partido="DEM       " UF="BA" Voto="Sim            " />
        <Deputado Nome="José Rocha" ideCadastro="74554" Partido="PR        " UF="BA" Voto="Sim            " />
        <Deputado Nome="Antonio Carlos Magalhães Neto" ideCadastro="74058" Partido="DEM       " UF="BA" Voto="Sim            " />
        <Deputado Nome="Paulo Magalhães" ideCadastro="74574" Partido="DEM       " UF="BA" Voto="Sim            " />
        <Deputado Nome="José Carlos Aleluia" ideCadastro="74553" Partido="DEM       " UF="BA" Voto="Sim            " />
        <Deputado Nome="Fernando de Fabinho" ideCadastro="74063" Partido="DEM       " UF="BA" Voto="Sim            " />
        <Deputado Nome="Fábio Souto" ideCadastro="74062" Partido="DEM       " UF="BA" Voto="Sim            " />
        <Deputado Nome="Luiz Carreira" ideCadastro="74142" Partido="DEM       " UF="BA" Voto="Sim            " />
        <Deputado Nome="Jutahy Junior" ideCadastro="74570" Partido="PSDB      " UF="BA" Voto="Sim            " />
        <Deputado Nome="Alice Portugal" ideCadastro="74057" Partido="PCdoB     " UF="BA" Voto="Sim            " />
        <Deputado Nome="Daniel Almeida" ideCadastro="74060" Partido="PCdoB     " UF="BA" Voto="Sim            " />
        <Deputado Nome="Marcelo Teixeira" ideCadastro="74300" Partido="PR        " UF="CE" Voto="Sim            " />
        <Deputado Nome="Mauro Benevides" ideCadastro="73588" Partido="PMDB      " UF="CE" Voto="Sim            " />
        <Deputado Nome="Zé Gerardo" ideCadastro="74309" Partido="PMDB      " UF="CE" Voto="Sim            " />
        <Deputado Nome="Pastor Pedro Ribeiro" ideCadastro="74032" Partido="PMDB      " UF="CE" Voto="Sim            " />
        <Deputado Nome="Manoel Salviano" ideCadastro="74456" Partido="PSDB      " UF="CE" Voto="Sim            " />
        <Deputado Nome="Vicente Arruda" ideCadastro="74308" Partido="PR        " UF="CE" Voto="Sim            " />
        <Deputado Nome="Tadeu Filippelli" ideCadastro="74806" Partido="PMDB      " UF="DF" Voto="Sim            " />
        <Deputado Nome="Osório Adriano" ideCadastro="73660" Partido="DEM       " UF="DF" Voto="Sim            " />
        <Deputado Nome="Tatico" ideCadastro="74289" Partido="PTB       " UF="GO" Voto="Sim            " />
        <Deputado Nome="Manato" ideCadastro="74163" Partido="PDT       " UF="ES" Voto="Sim            " />
        <Deputado Nome="Iriny Lopes" ideCadastro="74162" Partido="PT        " UF="ES" Voto="Sim            " />
        <Deputado Nome="Neucimar Fraga" ideCadastro="74165" Partido="PR        " UF="ES" Voto="Sim            " />
        <Deputado Nome="Rose de Freitas" ideCadastro="73507" Partido="PMDB      " UF="ES" Voto="Sim            " />
        <Deputado Nome="Roberto Balestra" ideCadastro="73674" Partido="PP        " UF="GO" Voto="Sim            " />
        <Deputado Nome="Leonardo Vilela" ideCadastro="74368" Partido="PSDB      " UF="GO" Voto="Sim            " />
        <Deputado Nome="Leandro Vilela" ideCadastro="74367" Partido="PMDB      " UF="GO" Voto="Sim            " />
        <Deputado Nome="Luiz Bittencourt" ideCadastro="74810" Partido="PMDB      " UF="GO" Voto="Sim            " />
        <Deputado Nome="Pedro Chaves" ideCadastro="74812" Partido="PMDB      " UF="GO" Voto="Sim            " />
        <Deputado Nome="Sandro Mabel" ideCadastro="73676" Partido="PR        " UF="GO" Voto="Sim            " />
        <Deputado Nome="Ronaldo Caiado" ideCadastro="74813" Partido="DEM       " UF="GO" Voto="Sim            " />
        <Deputado Nome="Carlos Alberto Leréia" ideCadastro="74290" Partido="PSDB      " UF="GO" Voto="Sim            " />
        <Deputado Nome="João Campos" ideCadastro="74366" Partido="PSDB      " UF="GO" Voto="Sim            " />
        <Deputado Nome="Pedro Novais" ideCadastro="74207" Partido="PMDB      " UF="MA" Voto="Sim            " />
        <Deputado Nome="Gastão Vieira" ideCadastro="74200" Partido="PMDB      " UF="MA" Voto="Sim            " />
        <Deputado Nome="Pedro Fernandes" ideCadastro="74449" Partido="PTB       " UF="MA" Voto="Sim            " />
        <Deputado Nome="Clóvis Fecury" ideCadastro="74026" Partido="DEM       " UF="MA" Voto="Sim            " />
        <Deputado Nome="Sebastião Madeira" ideCadastro="74211" Partido="PSDB      " UF="MA" Voto="Sim            " />
        <Deputado Nome="Edmar Moreira" ideCadastro="74580" Partido="DEM       " UF="MG" Voto="Sim            " />
        <Deputado Nome="Márcio Reinaldo Moreira" ideCadastro="74744" Partido="PP        " UF="MG" Voto="Sim            " />
        <Deputado Nome="Mário Heringer" ideCadastro="74158" Partido="PDT       " UF="MG" Voto="Sim            " />
        <Deputado Nome="Maria do Carmo Lara" ideCadastro="74586" Partido="PT        " UF="MG" Voto="Sim            " />
        <Deputado Nome="Odair Cunha" ideCadastro="74159" Partido="PT        " UF="MG" Voto="Sim            " />
        <Deputado Nome="Virgílio Guimarães" ideCadastro="74593" Partido="PT        " UF="MG" Voto="Sim            " />
        <Deputado Nome="Reginaldo Lopes" ideCadastro="74161" Partido="PT        " UF="MG" Voto="Sim            " />
        <Deputado Nome="Gilmar Machado" ideCadastro="74581" Partido="PT        " UF="MG" Voto="Sim            " />
        <Deputado Nome="Mauro Lopes" ideCadastro="74749" Partido="PMDB      " UF="MG" Voto="Sim            " />
        <Deputado Nome="Maria Lúcia Cardoso" ideCadastro="74587" Partido="PMDB      " UF="MG" Voto="Sim            " />
        <Deputado Nome="Saraiva Felipe" ideCadastro="74762" Partido="PMDB      " UF="MG" Voto="Sim            " />
        <Deputado Nome="Lincoln Portela" ideCadastro="74585" Partido="PR        " UF="MG" Voto="Sim            " />
        <Deputado Nome="Júlio Delgado" ideCadastro="73586" Partido="PSB       " UF="MG" Voto="Sim            " />
        <Deputado Nome="Ademir Camilo" ideCadastro="133374" Partido="PDT       " UF="MG" Voto="Sim            " />
        <Deputado Nome="Geraldo Thadeu" ideCadastro="74151" Partido="PPS       " UF="MG" Voto="Sim            " />
        <Deputado Nome="Lael Varella" ideCadastro="74742" Partido="DEM       " UF="MG" Voto="Sim            " />
        <Deputado Nome="José Santana de Vasconcellos" ideCadastro="74741" Partido="PR        " UF="MG" Voto="Sim            " />
        <Deputado Nome="Narcio Rodrigues" ideCadastro="74108" Partido="PSDB      " UF="MG" Voto="Art. 17        " />
        <Deputado Nome="Eduardo Barbosa" ideCadastro="74655" Partido="PSDB      " UF="MG" Voto="Sim            " />
        <Deputado Nome="Custódio Mattos" ideCadastro="74579" Partido="PSDB      " UF="MG" Voto="Sim            " />
        <Deputado Nome="Bonifácio de Andrada" ideCadastro="74650" Partido="PSDB      " UF="MG" Voto="Sim            " />
        <Deputado Nome="Rafael Guerra" ideCadastro="74590" Partido="PSDB      " UF="MG" Voto="Sim            " />
        <Deputado Nome="Antônio Carlos Biffi" ideCadastro="74373" Partido="PT        " UF="MS" Voto="Sim            " />
        <Deputado Nome="Vander Loubet" ideCadastro="74376" Partido="PT        " UF="MS" Voto="Sim            " />
        <Deputado Nome="Nelson Trad" ideCadastro="73761" Partido="PMDB      " UF="MS" Voto="Sim            " />
        <Deputado Nome="Waldemir Moka" ideCadastro="73456" Partido="PMDB      " UF="MS" Voto="Sim            " />
        <Deputado Nome="Antonio Cruz" ideCadastro="73817" Partido="PP        " UF="MS" Voto="Sim            " />
        <Deputado Nome="Geraldo Resende" ideCadastro="74374" Partido="PMDB      " UF="MS" Voto="Sim            " />
        <Deputado Nome="Pedro Henry" ideCadastro="74111" Partido="PP        " UF="MT" Voto="Sim            " />
        <Deputado Nome="Carlos Abicalil" ideCadastro="74285" Partido="PT        " UF="MT" Voto="Sim            " />
        <Deputado Nome="Wellington Fagundes" ideCadastro="73653" Partido="PR        " UF="MT" Voto="Sim            " />
        <Deputado Nome="Thelma de Oliveira" ideCadastro="74286" Partido="PSDB      " UF="MT" Voto="Sim            " />
        <Deputado Nome="Paulo Rocha" ideCadastro="74082" Partido="PT        " UF="PA" Voto="Sim            " />
        <Deputado Nome="Zé Geraldo" ideCadastro="73931" Partido="PT        " UF="PA" Voto="Sim            " />
        <Deputado Nome="Asdrubal Bentes" ideCadastro="74222" Partido="PMDB      " UF="PA" Voto="Sim            " />
        <Deputado Nome="Zenaldo Coutinho" ideCadastro="74354" Partido="PSDB      " UF="PA" Voto="Sim            " />
        <Deputado Nome="Luiz Couto" ideCadastro="74041" Partido="PT        " UF="PB" Voto="Sim            " />
        <Deputado Nome="Wellington Roberto" ideCadastro="74043" Partido="PR        " UF="PB" Voto="Sim            " />
        <Deputado Nome="Wilson Santiago" ideCadastro="74044" Partido="PMDB      " UF="PB" Voto="Sim            " />
        <Deputado Nome="Damião Feliciano" ideCadastro="74467" Partido="PDT       " UF="PB" Voto="Sim            " />
        <Deputado Nome="Armando Abílio" ideCadastro="74405" Partido="PTB       " UF="PB" Voto="Sim            " />
        <Deputado Nome="Maurício Rands" ideCadastro="74045" Partido="PT        " UF="PE" Voto="Sim            " />
        <Deputado Nome="Fernando Ferro" ideCadastro="74417" Partido="PT        " UF="PE" Voto="Sim            " />
        <Deputado Nome="Paulo Rubem Santiago" ideCadastro="74047" Partido="PDT       " UF="PE" Voto="Sim            " />
        <Deputado Nome="Raul Jungmann" ideCadastro="74048" Partido="PPS       " UF="PE" Voto="Sim            " />
        <Deputado Nome="Carlos Eduardo Cadoca" ideCadastro="74474" Partido="PSC       " UF="PE" Voto="Sim            " />
        <Deputado Nome="José Chaves" ideCadastro="74423" Partido="PTB       " UF="PE" Voto="Sim            " />
        <Deputado Nome="José Mendonça Bezerra" ideCadastro="74425" Partido="DEM       " UF="PE" Voto="Sim            " />
        <Deputado Nome="Gonzaga Patriota" ideCadastro="74419" Partido="PSB       " UF="PE" Voto="Sim            " />
        <Deputado Nome="Roberto Magalhães" ideCadastro="74433" Partido="DEM       " UF="PE" Voto="Sim            " />
        <Deputado Nome="Renildo Calheiros" ideCadastro="73801" Partido="PCdoB     " UF="PE" Voto="Sim            " />
        <Deputado Nome="Nazareno Fonteles" ideCadastro="74491" Partido="PT        " UF="PI" Voto="Sim            " />
        <Deputado Nome="Marcelo Castro" ideCadastro="74460" Partido="PMDB      " UF="PI" Voto="Sim            " />
        <Deputado Nome="Paes Landim" ideCadastro="74319" Partido="PTB       " UF="PI" Voto="Sim            " />
        <Deputado Nome="Júlio Cesar" ideCadastro="74317" Partido="DEM       " UF="PI" Voto="Sim            " />
        <Deputado Nome="Átila Lira" ideCadastro="74459" Partido="PSB       " UF="PI" Voto="Sim            " />
        <Deputado Nome="Nelson Meurer" ideCadastro="73781" Partido="PP        " UF="PR" Voto="Sim            " />
        <Deputado Nome="Dilceu Sperafico" ideCadastro="73768" Partido="PP        " UF="PR" Voto="Sim            " />
        <Deputado Nome="Ricardo Barros" ideCadastro="73788" Partido="PP        " UF="PR" Voto="Sim            " />
        <Deputado Nome="André Zacharow" ideCadastro="74377" Partido="PMDB      " UF="PR" Voto="Sim            " />
        <Deputado Nome="Dr. Rosinha" ideCadastro="73459" Partido="PT        " UF="PR" Voto="Sim            " />
        <Deputado Nome="Assis do Couto" ideCadastro="74378" Partido="PT        " UF="PR" Voto="Sim            " />
        <Deputado Nome="Airton Roveda" ideCadastro="73457" Partido="PR        " UF="PR" Voto="Sim            " />
        <Deputado Nome="Moacir Micheletto" ideCadastro="74238" Partido="PMDB      " UF="PR" Voto="Sim            " />
        <Deputado Nome="Gustavo Fruet" ideCadastro="73460" Partido="PSDB      " UF="PR" Voto="Sim            " />
        <Deputado Nome="Cezar Silvestri" ideCadastro="74379" Partido="PPS       " UF="PR" Voto="Sim            " />
        <Deputado Nome="Eduardo Sciarra" ideCadastro="74382" Partido="DEM       " UF="PR" Voto="Sim            " />
        <Deputado Nome="Affonso Camargo" ideCadastro="73765" Partido="PSDB      " UF="PR" Voto="Sim            " />
        <Deputado Nome="Chico da Princesa" ideCadastro="74000" Partido="PR        " UF="PR" Voto="Sim            " />
        <Deputado Nome="Odílio Balbinotti" ideCadastro="73782" Partido="PMDB      " UF="PR" Voto="Sim            " />
        <Deputado Nome="Jair Bolsonaro" ideCadastro="74847" Partido="PP        " UF="RJ" Voto="Sim            " />
        <Deputado Nome="Simão Sessim" ideCadastro="73424" Partido="PP        " UF="RJ" Voto="Sim            " />
        <Deputado Nome="Eduardo Cunha" ideCadastro="74173" Partido="PMDB      " UF="RJ" Voto="Sim            " />
        <Deputado Nome="Miro Teixeira" ideCadastro="74862" Partido="PDT       " UF="RJ" Voto="Sim            " />
        <Deputado Nome="Carlos Santana" ideCadastro="74835" Partido="PT        " UF="RJ" Voto="Sim            " />
        <Deputado Nome="Chico Alencar" ideCadastro="74171" Partido="PSOL      " UF="RJ" Voto="Sim            " />
        <Deputado Nome="Luiz Sérgio" ideCadastro="74688" Partido="PT        " UF="RJ" Voto="Sim            " />
        <Deputado Nome="Jorge Bittar" ideCadastro="74686" Partido="PT        " UF="RJ" Voto="Sim            " />
        <Deputado Nome="Antonio Carlos Biscaia" ideCadastro="73492" Partido="PT        " UF="RJ" Voto="Sim            " />
        <Deputado Nome="Arolde de Oliveira" ideCadastro="74833" Partido="DEM       " UF="RJ" Voto="Sim            " />
        <Deputado Nome="Rodrigo Maia" ideCadastro="74693" Partido="DEM       " UF="RJ" Voto="Sim            " />
        <Deputado Nome="Bernardo Ariston" ideCadastro="74169" Partido="PMDB      " UF="RJ" Voto="Sim            " />
        <Deputado Nome="Edson Ezequiel" ideCadastro="74838" Partido="PMDB      " UF="RJ" Voto="Sim            " />
        <Deputado Nome="Fernando Lopes" ideCadastro="74843" Partido="PMDB      " UF="RJ" Voto="Sim            " />
        <Deputado Nome="Alexandre Santos" ideCadastro="74830" Partido="PMDB      " UF="RJ" Voto="Sim            " />
        <Deputado Nome="Fátima Bezerra" ideCadastro="74037" Partido="PT        " UF="RN" Voto="Sim            " />
        <Deputado Nome="Sandra Rosado" ideCadastro="74039" Partido="PSB       " UF="RN" Voto="Sim            " />
        <Deputado Nome="Betinho Rosado" ideCadastro="74321" Partido="DEM       " UF="RN" Voto="Sim            " />
        <Deputado Nome="Anselmo de Jesus" ideCadastro="73937" Partido="PT        " UF="RO" Voto="Sim            " />
        <Deputado Nome="Eduardo Valverde" ideCadastro="73938" Partido="PT        " UF="RO" Voto="Sim            " />
        <Deputado Nome="Marinha Raupp" ideCadastro="74177" Partido="PMDB      " UF="RO" Voto="Sim            " />
        <Deputado Nome="Natan Donadon" ideCadastro="133372" Partido="PMDB      " UF="RO" Voto="Sim            " />
        <Deputado Nome="Maria Helena" ideCadastro="64960" Partido="PSB       " UF="RR" Voto="Sim            " />
        <Deputado Nome="Francisco Rodrigues" ideCadastro="73981" Partido="DEM       " UF="RR" Voto="Sim            " />
        <Deputado Nome="Afonso Hamm" ideCadastro="136811" Partido="PP        " UF="RS" Voto="Sim            " />
        <Deputado Nome="Tarcísio Zimmermann" ideCadastro="73577" Partido="PT        " UF="RS" Voto="Sim            " />
        <Deputado Nome="Marco Maia" ideCadastro="133373" Partido="PT        " UF="RS" Voto="Sim            " />
        <Deputado Nome="Adão Pretto" ideCadastro="73886" Partido="PT        " UF="RS" Voto="Sim            " />
        <Deputado Nome="Darcísio Perondi" ideCadastro="73891" Partido="PMDB      " UF="RS" Voto="Sim            " />
        <Deputado Nome="Mendes Ribeiro Filho" ideCadastro="73904" Partido="PMDB      " UF="RS" Voto="Sim            " />
        <Deputado Nome="Cezar Schirmer" ideCadastro="73480" Partido="PMDB      " UF="RS" Voto="Sim            " />
        <Deputado Nome="Eliseu Padilha" ideCadastro="73892" Partido="PMDB      " UF="RS" Voto="Sim            " />
        <Deputado Nome="Onyx Lorenzoni" ideCadastro="74399" Partido="DEM       " UF="RS" Voto="Sim            " />
        <Deputado Nome="Zonta" ideCadastro="74392" Partido="PP        " UF="SC" Voto="Sim            " />
        <Deputado Nome="Fernando Coruja" ideCadastro="73471" Partido="PPS       " UF="SC" Voto="Sim            " />
        <Deputado Nome="Carlito Merss" ideCadastro="73469" Partido="PT        " UF="SC" Voto="Sim            " />
        <Deputado Nome="Vignatti" ideCadastro="74391" Partido="PT        " UF="SC" Voto="Sim            " />
        <Deputado Nome="Edinho Bez" ideCadastro="73793" Partido="PMDB      " UF="SC" Voto="Sim            " />
        <Deputado Nome="Valdir Colatto" ideCadastro="74010" Partido="PMDB      " UF="SC" Voto="Sim            " />
        <Deputado Nome="João Matos" ideCadastro="73873" Partido="PMDB      " UF="SC" Voto="Sim            " />
        <Deputado Nome="Mendonça Prado" ideCadastro="74056" Partido="DEM       " UF="SE" Voto="Sim            " />
        <Deputado Nome="Jackson Barreto" ideCadastro="77701" Partido="PMDB      " UF="SE" Voto="Sim            " />
        <Deputado Nome="Celso Russomanno" ideCadastro="73441" Partido="PP        " UF="SP" Voto="Sim            " />
        <Deputado Nome="José Eduardo Cardozo" ideCadastro="74274" Partido="PT        " UF="SP" Voto="Sim            " />
        <Deputado Nome="Arlindo Chinaglia" ideCadastro="73433" Partido="PT        " UF="SP" Voto="Art. 17        " />
        <Deputado Nome="João Paulo Cunha" ideCadastro="73534" Partido="PT        " UF="SP" Voto="Sim            " />
        <Deputado Nome="Ivan Valente" ideCadastro="73531" Partido="PSOL      " UF="SP" Voto="Sim            " />
        <Deputado Nome="Ricardo Berzoini" ideCadastro="74793" Partido="PT        " UF="SP" Voto="Sim            " />
        <Deputado Nome="Devanir Ribeiro" ideCadastro="74264" Partido="PT        " UF="SP" Voto="Sim            " />
        <Deputado Nome="Vicentinho" ideCadastro="74283" Partido="PT        " UF="SP" Voto="Sim            " />
        <Deputado Nome="Paulo Cesar de Oliveira Lima" ideCadastro="73555" Partido="PMDB      " UF="SP" Voto="Sim            " />
        <Deputado Nome="Milton Monti" ideCadastro="74787" Partido="PR        " UF="SP" Voto="Sim            " />
        <Deputado Nome="Valdemar Costa Neto" ideCadastro="73565" Partido="PR        " UF="SP" Voto="Sim            " />
        <Deputado Nome="Luiza Erundina" ideCadastro="74784" Partido="PSB       " UF="SP" Voto="Sim            " />
        <Deputado Nome="Jefferson Campos" ideCadastro="74273" Partido="PTB       " UF="SP" Voto="Sim            " />
        <Deputado Nome="Marcelo Ortiz" ideCadastro="74278" Partido="PV        " UF="SP" Voto="Sim            " />
        <Deputado Nome="Carlos Sampaio" ideCadastro="74262" Partido="PSDB      " UF="SP" Voto="Sim            " />
        <Deputado Nome="Lobbe Neto" ideCadastro="74277" Partido="PSDB      " UF="SP" Voto="Sim            " />
        <Deputado Nome="Antonio Carlos Pannunzio" ideCadastro="73431" Partido="PSDB      " UF="SP" Voto="Sim            " />
        <Deputado Nome="Silvio Torres" ideCadastro="73560" Partido="PSDB      " UF="SP" Voto="Sim            " />
        <Deputado Nome="Julio Semeghini" ideCadastro="74783" Partido="PSDB      " UF="SP" Voto="Sim            " />
        <Deputado Nome="Aldo Rebelo" ideCadastro="73428" Partido="PCdoB     " UF="SP" Voto="Sim            " />
        <Deputado Nome="Osvaldo Reis" ideCadastro="74191" Partido="PMDB      " UF="TO" Voto="Sim            " />
        <Deputado Nome="Eduardo Gomes" ideCadastro="73945" Partido="PSDB      " UF="TO" Voto="Sim            " />
        <Deputado Nome="Fernando Melo" ideCadastro="141432" Partido="PT        " UF="AC" Voto="Sim            " />
        <Deputado Nome="Ilderlei Cordeiro" ideCadastro="141451" Partido="PPS       " UF="AC" Voto="Sim            " />
        <Deputado Nome="Sergio Petecão" ideCadastro="141541" Partido="PMN       " UF="AC" Voto="Sim            " />
        <Deputado Nome="Augusto Farias" ideCadastro="74441" Partido="PTB       " UF="AL" Voto="Sim            " />
        <Deputado Nome="Carlos Alberto Canuto" ideCadastro="141397" Partido="PMDB      " UF="AL" Voto="Sim            " />
        <Deputado Nome="Cristiano Matheus" ideCadastro="141410" Partido="PMDB      " UF="AL" Voto="Sim            " />
        <Deputado Nome="Joaquim Beltrão" ideCadastro="141461" Partido="PMDB      " UF="AL" Voto="Sim            " />
        <Deputado Nome="Francisco Tenorio" ideCadastro="141467" Partido="PMN       " UF="AL" Voto="Sim            " />
        <Deputado Nome="Francisco Praciano" ideCadastro="141438" Partido="PT        " UF="AM" Voto="Sim            " />
        <Deputado Nome="Marcelo Serafim" ideCadastro="141493" Partido="PSB       " UF="AM" Voto="Sim            " />
        <Deputado Nome="Rebecca Garcia" ideCadastro="141525" Partido="PP        " UF="AM" Voto="Sim            " />
        <Deputado Nome="Ronaldo Leite" ideCadastro="151214" Partido="PHS       " UF="AM" Voto="Sim            " />
        <Deputado Nome="Lucenira Pimentel" ideCadastro="141504" Partido="PR        " UF="AP" Voto="Sim            " />
        <Deputado Nome="Sebastião Bala Rocha" ideCadastro="141539" Partido="PDT       " UF="AP" Voto="Sim            " />
        <Deputado Nome="Edigar Mão Branca" ideCadastro="143253" Partido="PV        " UF="BA" Voto="Sim            " />
        <Deputado Nome="Geraldo Simões" ideCadastro="74566" Partido="PT        " UF="BA" Voto="Sim            " />
        <Deputado Nome="João Carlos Bacelar" ideCadastro="141458" Partido="PR        " UF="BA" Voto="Sim            " />
        <Deputado Nome="Lídice da Mata" ideCadastro="139285" Partido="PSB       " UF="BA" Voto="Sim            " />
        <Deputado Nome="Maurício Trindade" ideCadastro="141506" Partido="PR        " UF="BA" Voto="Sim            " />
        <Deputado Nome="Veloso" ideCadastro="141524" Partido="PMDB      " UF="BA" Voto="Sim            " />
        <Deputado Nome="Roberto Britto" ideCadastro="141529" Partido="PP        " UF="BA" Voto="Sim            " />
        <Deputado Nome="Sérgio Barradas Carneiro" ideCadastro="74533" Partido="PT        " UF="BA" Voto="Sim            " />
        <Deputado Nome="Sérgio Brito" ideCadastro="73808" Partido="PDT       " UF="BA" Voto="Sim            " />
        <Deputado Nome="Eudes Xavier" ideCadastro="141386" Partido="PT        " UF="CE" Voto="Sim            " />
        <Deputado Nome="Eugênio Rabelo" ideCadastro="141426" Partido="PP        " UF="CE" Voto="Sim            " />
        <Deputado Nome="Flávio Bezerra" ideCadastro="141435" Partido="PMDB      " UF="CE" Voto="Sim            " />
        <Deputado Nome="Chico Lopes" ideCadastro="141440" Partido="PCdoB     " UF="CE" Voto="Sim            " />
        <Deputado Nome="José Airton Cirilo" ideCadastro="141464" Partido="PT        " UF="CE" Voto="Sim            " />
        <Deputado Nome="Paulo Henrique Lustosa" ideCadastro="141517" Partido="PMDB      " UF="CE" Voto="Sim            " />
        <Deputado Nome="Magela" ideCadastro="74802" Partido="PT        " UF="DF" Voto="Sim            " />
        <Deputado Nome="Jofran Frejat" ideCadastro="73658" Partido="PR        " UF="DF" Voto="Sim            " />
        <Deputado Nome="Laerte Bessa" ideCadastro="141478" Partido="PMDB      " UF="DF" Voto="Sim            " />
        <Deputado Nome="Rodovalho" ideCadastro="141530" Partido="DEM       " UF="DF" Voto="Sim            " />
        <Deputado Nome="Rodrigo Rollemberg" ideCadastro="141533" Partido="PSB       " UF="DF" Voto="Sim            " />
        <Deputado Nome="Camilo Cola" ideCadastro="141395" Partido="PMDB      " UF="ES" Voto="Sim            " />
        <Deputado Nome="Jurandy Loureiro" ideCadastro="141475" Partido="PSC       " UF="ES" Voto="Sim            " />
        <Deputado Nome="Luiz Paulo Vellozo Lucas" ideCadastro="141489" Partido="PSDB      " UF="ES" Voto="Sim            " />
        <Deputado Nome="Rita Camata" ideCadastro="74777" Partido="PMDB      " UF="ES" Voto="Sim            " />
        <Deputado Nome="Sueli Vidigal" ideCadastro="141548" Partido="PDT       " UF="ES" Voto="Sim            " />
        <Deputado Nome="Lelo Coimbra" ideCadastro="141562" Partido="PMDB      " UF="ES" Voto="Sim            " />
        <Deputado Nome="Íris de Araújo" ideCadastro="141453" Partido="PMDB      " UF="GO" Voto="Sim            " />
        <Deputado Nome="Marcelo Melo" ideCadastro="141494" Partido="PMDB      " UF="GO" Voto="Sim            " />
        <Deputado Nome="Pedro Wilson" ideCadastro="73673" Partido="PT        " UF="GO" Voto="Sim            " />
        <Deputado Nome="Carlos Brandão" ideCadastro="141402" Partido="PSDB      " UF="MA" Voto="Sim            " />
        <Deputado Nome="Cleber Verde" ideCadastro="141408" Partido="PRB       " UF="MA" Voto="Sim            " />
        <Deputado Nome="Davi Alves Silva Júnior" ideCadastro="141412" Partido="PDT       " UF="MA" Voto="Sim            " />
        <Deputado Nome="Domingos Dutra" ideCadastro="74197" Partido="PT        " UF="MA" Voto="Sim            " />
        <Deputado Nome="Flávio Dino" ideCadastro="141436" Partido="PCdoB     " UF="MA" Voto="Sim            " />
        <Deputado Nome="Pinto Itamaraty" ideCadastro="141465" Partido="PSDB      " UF="MA" Voto="Sim            " />
        <Deputado Nome="Julião Amin" ideCadastro="141474" Partido="PDT       " UF="MA" Voto="Sim            " />
        <Deputado Nome="Professor Setimo" ideCadastro="141543" Partido="PMDB      " UF="MA" Voto="Sim            " />
        <Deputado Nome="Waldir Maranhão" ideCadastro="141558" Partido="PP        " UF="MA" Voto="Sim            " />
        <Deputado Nome="Aelton Freitas" ideCadastro="141372" Partido="PR        " UF="MG" Voto="Sim            " />
        <Deputado Nome="Antônio Andrade" ideCadastro="141387" Partido="PMDB      " UF="MG" Voto="Sim            " />
        <Deputado Nome="Antônio Roberto" ideCadastro="141390" Partido="PV        " UF="MG" Voto="Sim            " />
        <Deputado Nome="Ciro Pedrosa" ideCadastro="141407" Partido="PV        " UF="MG" Voto="Sim            " />
        <Deputado Nome="Elismar Prado" ideCadastro="141424" Partido="PT        " UF="MG" Voto="Sim            " />
        <Deputado Nome="Humberto Souto" ideCadastro="74662" Partido="PPS       " UF="MG" Voto="Sim            " />
        <Deputado Nome="José Fernando Aparecido de Oliveira" ideCadastro="141466" Partido="PV        " UF="MG" Voto="Sim            " />
        <Deputado Nome="Miguel Martini" ideCadastro="141469" Partido="PHS       " UF="MG" Voto="Sim            " />
        <Deputado Nome="Juvenil" ideCadastro="141477" Partido="PRTB      " UF="MG" Voto="Sim            " />
        <Deputado Nome="Leonardo Quintão" ideCadastro="141482" Partido="PMDB      " UF="MG" Voto="Sim            " />
        <Deputado Nome="Marcos Montes" ideCadastro="141500" Partido="DEM       " UF="MG" Voto="Sim            " />
        <Deputado Nome="Jô Moraes" ideCadastro="141503" Partido="PCdoB     " UF="MG" Voto="Sim            " />
        <Deputado Nome="Bilac Pinto" ideCadastro="141513" Partido="PR        " UF="MG" Voto="Sim            " />
        <Deputado Nome="Paulo Abi-Ackel" ideCadastro="141516" Partido="PSDB      " UF="MG" Voto="Sim            " />
        <Deputado Nome="Paulo Piau" ideCadastro="141519" Partido="PMDB      " UF="MG" Voto="Sim            " />
        <Deputado Nome="Rodrigo de Castro" ideCadastro="141531" Partido="PSDB      " UF="MG" Voto="Sim            " />
        <Deputado Nome="Vitor Penido" ideCadastro="141557" Partido="DEM       " UF="MG" Voto="Sim            " />
        <Deputado Nome="Dagoberto" ideCadastro="141411" Partido="PDT       " UF="MS" Voto="Sim            " />
        <Deputado Nome="Eliene Lima" ideCadastro="141423" Partido="PP        " UF="MT" Voto="Sim            " />
        <Deputado Nome="Homero Pereira" ideCadastro="141448" Partido="PR        " UF="MT" Voto="Sim            " />
        <Deputado Nome="Valtenir Pereira" ideCadastro="141552" Partido="PSB       " UF="MT" Voto="Sim            " />
        <Deputado Nome="Elcione Barbalho" ideCadastro="74075" Partido="PMDB      " UF="PA" Voto="Sim            " />
        <Deputado Nome="Gerson Peres" ideCadastro="74076" Partido="PP        " UF="PA" Voto="Sim            " />
        <Deputado Nome="Giovanni Queiroz" ideCadastro="74077" Partido="PDT       " UF="PA" Voto="Sim            " />
        <Deputado Nome="Beto Faro" ideCadastro="141335" Partido="PT        " UF="PA" Voto="Sim            " />
        <Deputado Nome="Lúcio Vale" ideCadastro="141484" Partido="PR        " UF="PA" Voto="Sim            " />
        <Deputado Nome="Wandenkolk Gonçalves" ideCadastro="141561" Partido="PSDB      " UF="PA" Voto="Sim            " />
        <Deputado Nome="Manoel Junior" ideCadastro="141490" Partido="PSB       " UF="PB" Voto="Sim            " />
        <Deputado Nome="Vital do Rêgo Filho" ideCadastro="141556" Partido="PMDB      " UF="PB" Voto="Sim            " />
        <Deputado Nome="Edgar Moury" ideCadastro="141416" Partido="PMDB      " UF="PE" Voto="Sim            " />
        <Deputado Nome="Pedro Eugênio" ideCadastro="74556" Partido="PT        " UF="PE" Voto="Sim            " />
        <Deputado Nome="Silvio Costa" ideCadastro="4930" Partido="PMN       " UF="PE" Voto="Sim            " />
        <Deputado Nome="Wolney Queiroz" ideCadastro="74439" Partido="PDT       " UF="PE" Voto="Sim            " />
        <Deputado Nome="Mainha" ideCadastro="151965" Partido="DEM       " UF="PI" Voto="Sim            " />
        <Deputado Nome="Osmar Júnior" ideCadastro="141514" Partido="PCdoB     " UF="PI" Voto="Sim            " />
        <Deputado Nome="Alceni Guerra" ideCadastro="139133" Partido="DEM       " UF="PR" Voto="Sim            " />
        <Deputado Nome="Andre Vargas" ideCadastro="141378" Partido="PT        " UF="PR" Voto="Sim            " />
        <Deputado Nome="Ratinho Junior" ideCadastro="141403" Partido="PSC       " UF="PR" Voto="Sim            " />
        <Deputado Nome="Barbosa Neto" ideCadastro="141449" Partido="PDT       " UF="PR" Voto="Sim            " />
        <Deputado Nome="Alfredo Kaefer" ideCadastro="141454" Partido="PSDB      " UF="PR" Voto="Abstenção      " />
        <Deputado Nome="Luiz Carlos Setim" ideCadastro="141486" Partido="DEM       " UF="PR" Voto="Sim            " />
        <Deputado Nome="Marcelo Almeida" ideCadastro="146613" Partido="PMDB      " UF="PR" Voto="Sim            " />
        <Deputado Nome="Rodrigo Rocha Loures" ideCadastro="141532" Partido="PMDB      " UF="PR" Voto="Sim            " />
        <Deputado Nome="Dr. Adilson Soares" ideCadastro="141371" Partido="PR        " UF="RJ" Voto="Sim            " />
        <Deputado Nome="Andreia Zito" ideCadastro="141379" Partido="PSDB      " UF="RJ" Voto="Sim            " />
        <Deputado Nome="Indio da Costa" ideCadastro="141389" Partido="DEM       " UF="RJ" Voto="Sim            " />
        <Deputado Nome="Arnaldo Vianna" ideCadastro="141392" Partido="PDT       " UF="RJ" Voto="Sim            " />
        <Deputado Nome="Edmilson Valentim" ideCadastro="139187" Partido="PCdoB     " UF="RJ" Voto="Sim            " />
        <Deputado Nome="Eduardo Lopes" ideCadastro="4928" Partido="PSB       " UF="RJ" Voto="Sim            " />
        <Deputado Nome="Filipe Pereira" ideCadastro="141433" Partido="PSC       " UF="RJ" Voto="Sim            " />
        <Deputado Nome="Geraldo Pudim" ideCadastro="141442" Partido="PMDB      " UF="RJ" Voto="Sim            " />
        <Deputado Nome="Hugo Leal" ideCadastro="141450" Partido="PSC       " UF="RJ" Voto="Sim            " />
        <Deputado Nome="Léo Vivas" ideCadastro="141452" Partido="PRB       " UF="RJ" Voto="Sim            " />
        <Deputado Nome="Leandro Sampaio" ideCadastro="141481" Partido="PPS       " UF="RJ" Voto="Sim            " />
        <Deputado Nome="Pastor Manoel Ferreira" ideCadastro="141491" Partido="PTB       " UF="RJ" Voto="Sim            " />
        <Deputado Nome="Marcelo Itagiba" ideCadastro="141495" Partido="PMDB      " UF="RJ" Voto="Sim            " />
        <Deputado Nome="Neilton Mulim" ideCadastro="141510" Partido="PR        " UF="RJ" Voto="Sim            " />
        <Deputado Nome="Otavio Leite" ideCadastro="141515" Partido="PSDB      " UF="RJ" Voto="Sim            " />
        <Deputado Nome="Rogerio Lisboa" ideCadastro="141534" Partido="DEM       " UF="RJ" Voto="Sim            " />
        <Deputado Nome="Silvio Lopes" ideCadastro="73998" Partido="PSDB      " UF="RJ" Voto="Sim            " />
        <Deputado Nome="Solange Amaral" ideCadastro="141546" Partido="DEM       " UF="RJ" Voto="Sim            " />
        <Deputado Nome="Solange Almeida" ideCadastro="141547" Partido="PMDB      " UF="RJ" Voto="Sim            " />
        <Deputado Nome="Vinicius Carvalho" ideCadastro="141555" Partido="PTdoB     " UF="RJ" Voto="Sim            " />
        <Deputado Nome="Fábio Faria" ideCadastro="141428" Partido="PMN       " UF="RN" Voto="Sim            " />
        <Deputado Nome="Felipe Maia" ideCadastro="141429" Partido="DEM       " UF="RN" Voto="Sim            " />
        <Deputado Nome="João Maia" ideCadastro="141459" Partido="PR        " UF="RN" Voto="Sim            " />
        <Deputado Nome="Rogério Marinho" ideCadastro="141535" Partido="PSB       " UF="RN" Voto="Sim            " />
        <Deputado Nome="Ernandes Amorim" ideCadastro="141425" Partido="PTB       " UF="RO" Voto="Sim            " />
        <Deputado Nome="Lindomar Garçon" ideCadastro="141483" Partido="PV        " UF="RO" Voto="Sim            " />
        <Deputado Nome="Mauro Nazif" ideCadastro="141508" Partido="PSB       " UF="RO" Voto="Sim            " />
        <Deputado Nome="Edio Lopes" ideCadastro="141417" Partido="PMDB      " UF="RR" Voto="Sim            " />
        <Deputado Nome="Marcio Junqueira" ideCadastro="141496" Partido="DEM       " UF="RR" Voto="Sim            " />
        <Deputado Nome="Neudo Campos" ideCadastro="141512" Partido="PP        " UF="RR" Voto="Sim            " />
        <Deputado Nome="Germano Bonow" ideCadastro="141443" Partido="DEM       " UF="RS" Voto="Sim            " />
        <Deputado Nome="Pepe Vargas" ideCadastro="141445" Partido="PT        " UF="RS" Voto="Sim            " />
        <Deputado Nome="Luiz Carlos Busato" ideCadastro="141485" Partido="PTB       " UF="RS" Voto="Sim            " />
        <Deputado Nome="Manuela DÁvila" ideCadastro="141492" Partido="PCdoB     " UF="RS" Voto="Sim            " />
        <Deputado Nome="Renato Molling" ideCadastro="141527" Partido="PP        " UF="RS" Voto="Sim            " />
        <Deputado Nome="Professor Ruy Pauletti" ideCadastro="141538" Partido="PSDB      " UF="RS" Voto="Sim            " />
        <Deputado Nome="Vilson Covatti" ideCadastro="141870" Partido="PP        " UF="RS" Voto="Sim            " />
        <Deputado Nome="Angela Amin" ideCadastro="73696" Partido="PP        " UF="SC" Voto="Sim            " />
        <Deputado Nome="Celso Maldaner" ideCadastro="141405" Partido="PMDB      " UF="SC" Voto="Sim            " />
        <Deputado Nome="Décio Lima" ideCadastro="141413" Partido="PT        " UF="SC" Voto="Sim            " />
        <Deputado Nome="Mauro Mariani" ideCadastro="141507" Partido="PMDB      " UF="SC" Voto="Sim            " />
        <Deputado Nome="Nelson Goetten" ideCadastro="141511" Partido="PR        " UF="SC" Voto="Sim            " />
        <Deputado Nome="Paulo Bornhausen" ideCadastro="73883" Partido="DEM       " UF="SC" Voto="Sim            " />
        <Deputado Nome="Valadares Filho" ideCadastro="141384" Partido="PSB       " UF="SE" Voto="Sim            " />
        <Deputado Nome="Eduardo Amorim" ideCadastro="141420" Partido="PSC       " UF="SE" Voto="Sim            " />
        <Deputado Nome="Jerônimo Reis" ideCadastro="74528" Partido="DEM       " UF="SE" Voto="Sim            " />
        <Deputado Nome="Iran Barbosa" ideCadastro="141468" Partido="PT        " UF="SE" Voto="Sim            " />
        <Deputado Nome="Aline Corrêa" ideCadastro="141375" Partido="PP        " UF="SP" Voto="Sim            " />
        <Deputado Nome="Antonio Palocci" ideCadastro="74701" Partido="PT        " UF="SP" Voto="Sim            " />
        <Deputado Nome="Arnaldo Jardim" ideCadastro="141391" Partido="PPS       " UF="SP" Voto="Sim            " />
        <Deputado Nome="Cândido Vaccarezza" ideCadastro="141396" Partido="PT        " UF="SP" Voto="Sim            " />
        <Deputado Nome="Carlos Zarattini" ideCadastro="141398" Partido="PT        " UF="SP" Voto="Sim            " />
        <Deputado Nome="Clodovil Hernandes" ideCadastro="141409" Partido="PR        " UF="SP" Voto="Sim            " />
        <Deputado Nome="Emanuel Fernandes" ideCadastro="74119" Partido="PSDB      " UF="SP" Voto="Sim            " />
        <Deputado Nome="Fernando Chucre" ideCadastro="141344" Partido="PSDB      " UF="SP" Voto="Sim            " />
        <Deputado Nome="Frank Aguiar" ideCadastro="141437" Partido="PTB       " UF="SP" Voto="Sim            " />
        <Deputado Nome="Guilherme Campos" ideCadastro="141447" Partido="DEM       " UF="SP" Voto="Sim            " />
        <Deputado Nome="Janete Rocha Pietá" ideCadastro="141455" Partido="PT        " UF="SP" Voto="Sim            " />
        <Deputado Nome="Jilmar Tatto" ideCadastro="141456" Partido="PT        " UF="SP" Voto="Sim            " />
        <Deputado Nome="João Dado" ideCadastro="73682" Partido="PDT       " UF="SP" Voto="Sim            " />
        <Deputado Nome="Jorginho Maluly" ideCadastro="4927" Partido="DEM       " UF="SP" Voto="Sim            " />
        <Deputado Nome="Jorge Tadeu Mudalen" ideCadastro="73535" Partido="DEM       " UF="SP" Voto="Sim            " />
        <Deputado Nome="José Genoíno" ideCadastro="73540" Partido="PT        " UF="SP" Voto="Sim            " />
        <Deputado Nome="José Paulo Tóffano" ideCadastro="141471" Partido="PV        " UF="SP" Voto="Sim            " />
        <Deputado Nome="Ricardo Tripoli" ideCadastro="141472" Partido="PSDB      " UF="SP" Voto="Sim            " />
        <Deputado Nome="Roberto Santiago" ideCadastro="141473" Partido="PV        " UF="SP" Voto="Sim            " />
        <Deputado Nome="Paulo Teixeira" ideCadastro="141488" Partido="PT        " UF="SP" Voto="Sim            " />
        <Deputado Nome="Dr. Ubiali" ideCadastro="141498" Partido="PSB       " UF="SP" Voto="Sim            " />
        <Deputado Nome="Paulo Renato Souza" ideCadastro="141520" Partido="PSDB      " UF="SP" Voto="Sim            " />
        <Deputado Nome="Regis de Oliveira" ideCadastro="73556" Partido="PSC       " UF="SP" Voto="Sim            " />
        <Deputado Nome="Reinaldo Nogueira" ideCadastro="141526" Partido="PDT       " UF="SP" Voto="Sim            " />
        <Deputado Nome="Renato Amary" ideCadastro="141528" Partido="PSDB      " UF="SP" Voto="Sim            " />
        <Deputado Nome="Dr. Nechar" ideCadastro="141540" Partido="PV        " UF="SP" Voto="Sim            " />
        <Deputado Nome="Silvinho Peccioli" ideCadastro="141545" Partido="DEM       " UF="SP" Voto="Sim            " />
        <Deputado Nome="Dr. Talmir" ideCadastro="141550" Partido="PV        " UF="SP" Voto="Sim            " />
        <Deputado Nome="Vanderlei Macris" ideCadastro="141553" Partido="PSDB      " UF="SP" Voto="Sim            " />
        <Deputado Nome="Walter Ihoshi" ideCadastro="141560" Partido="DEM       " UF="SP" Voto="Sim            " />
        <Deputado Nome="William Woo" ideCadastro="141563" Partido="PSDB      " UF="SP" Voto="Sim            " />
        <Deputado Nome="João Oliveira" ideCadastro="141460" Partido="DEM       " UF="TO" Voto="Sim            " />
        <Deputado Nome="Lázaro Botelho" ideCadastro="141480" Partido="PP        " UF="TO" Voto="Sim            " />
        <Deputado Nome="Moises Avelino" ideCadastro="139311" Partido="PMDB      " UF="TO" Voto="Sim            " />
        <Deputado Nome="NIlmar Ruiz" ideCadastro="73594" Partido="DEM       " UF="TO" Voto="Sim            " />
        <Deputado Nome="Vicentinho Alves" ideCadastro="141554" Partido="PR        " UF="TO" Voto="Sim            " />
      </votos>
    </Votacao>
  </Votacoes>
</proposicao>